{
  "tracks": {
    "track-044557bedb8a6276": {
      "id": "track-044557bedb8a6276",
      "title": "FREEPORT",
      "artist": "Ludwig Goransson",
      "album": "Tenet (Original Motion Picture Soundtrack) (Deluxe Edition)",
      "duration": 0,
      "file_path": "/home/jscyril/Music/FLAC/complete/Ludwig Goransson - FREEPORT.flac",
      "genre": "",
      "year": 2020,
      "track_number": 0,
      "created_at": "2026-01-28T16:20:22.446839708+05:30"
    },
    "track-06441f777f859321": {
      "id": "track-06441f777f859321",
      "title": "Victory Lap Five",
      "artist": "LYNY",
      "album": "Victory Lap Five",
      "duration": 0,
      "file_path": "/home/jscyril/Music/FLAC/complete/Fred again.. - Victory Lap Five.flac",
      "genre": "Dance",
      "year": 2025,
      "track_number": 1,
      "created_at": "2026-01-28T16:20:22.461043861+05:30"
    },
    "track-1208947d93f16033": {
      "id": "track-1208947d93f16033",
      "title": "Can You Hear The Music",
      "artist": "Ludwig Goransson",
      "album": "Oppenheimer (Original Motion Picture Soundtrack)",
      "duration": 0,
      "file_path": "/home/jscyril/Music/FLAC/complete/Ludwig Goransson - Can You Hear The Music (1).flac",
      "genre": "",
      "year": 2023,
      "track_number": 0,
      "created_at": "2026-01-28T16:20:22.445703427+05:30"
    },
    "track-13f5f2e27afcf728": {
      "id": "track-13f5f2e27afcf728",
      "title": "Cornfield Chase",
      "artist": "Hans Zimmer",
      "album": "Interstellar (Original Motion Picture Soundtrack) (Expanded Edition)",
      "duration": 0,
      "file_path": "/home/jscyril/Music/FLAC/complete/Hans Zimmer - Cornfield Chase.flac",
      "genre": "",
      "year": 2014,
      "track_number": 0,
      "created_at": "2026-01-28T16:20:22.444559371+05:30"
    },
    "track-14e134de254393be": {
      "id": "track-14e134de254393be",
      "title": "I Love It (Tiesto's Club Life Remix)",
      "artist": "Icona Pop",
      "album": "Club Life - Volume Three Stockholm (Unmixed Tracks)",
      "duration": 0,
      "file_path": "/home/jscyril/Music/FLAC/complete/08. Icona Pop - I Love It (Tiesto's Club Life Remix).flac",
      "genre": "House",
      "year": 2013,
      "track_number": 8,
      "created_at": "2026-01-28T16:20:22.433382225+05:30"
    },
    "track-17ba5a2bb159d676": {
      "id": "track-17ba5a2bb159d676",
      "title": "Sanctuary",
      "artist": "Joji",
      "album": "Nectar",
      "duration": 0,
      "file_path": "/home/jscyril/Music/FLAC/complete/Nectar/Joji_Nectar_08_Sanctuary.flac",
      "genre": "",
      "year": 2020,
      "track_number": 8,
      "created_at": "2026-01-28T16:20:22.451284165+05:30"
    },
    "track-1b4fc511fe3d2e7c": {
      "id": "track-1b4fc511fe3d2e7c",
      "title": "Test Drive",
      "artist": "Joji",
      "album": "BALLADS 1",
      "duration": 0,
      "file_path": "/home/jscyril/Music/FLAC/complete/BALLADS 1/Joji_BALLADS 1_03_TEST DRIVE.flac",
      "genre": "R\u0026B",
      "year": 2018,
      "track_number": 3,
      "created_at": "2026-01-28T16:20:22.43977696+05:30"
    },
    "track-1c00994cfc448583": {
      "id": "track-1c00994cfc448583",
      "title": "Pacifica",
      "artist": "Caleb Bryant",
      "album": "Pacifica",
      "duration": 0,
      "file_path": "/home/jscyril/Music/FLAC/complete/Caleb Bryant - Pacifica.flac",
      "genre": "",
      "year": 2023,
      "track_number": 0,
      "created_at": "2026-01-28T16:20:22.441962379+05:30"
    },
    "track-1cb25b2b015073bf": {
      "id": "track-1cb25b2b015073bf",
      "title": "My House Is Not A Home",
      "artist": "d4vd",
      "album": "My House Is Not A Home - Single",
      "duration": 0,
      "file_path": "/home/jscyril/Music/FLAC/complete/eluate/music/d4vd - My House Is Not A Home.flac",
      "genre": "Alternative",
      "year": 2024,
      "track_number": 1,
      "created_at": "2026-01-28T16:20:22.463821852+05:30"
    },
    "track-1da28ffd63804a0a": {
      "id": "track-1da28ffd63804a0a",
      "title": "Viva La Vida",
      "artist": "Coldplay",
      "album": "Viva La Vida or Death and All His Friends",
      "duration": 0,
      "file_path": "/home/jscyril/Music/FLAC/complete/Coldplay - Viva La Vida.flac",
      "genre": "",
      "year": 2009,
      "track_number": 0,
      "created_at": "2026-01-28T16:20:22.442941436+05:30"
    },
    "track-1e2ffa0006012f1f": {
      "id": "track-1e2ffa0006012f1f",
      "title": "Pretty Boy (feat. Lil Yachty)",
      "artist": "Joji",
      "album": "Nectar",
      "duration": 0,
      "file_path": "/home/jscyril/Music/FLAC/complete/Nectar/Joji_Nectar_11_Pretty Boy.flac",
      "genre": "",
      "year": 2020,
      "track_number": 11,
      "created_at": "2026-01-28T16:20:22.452586437+05:30"
    },
    "track-2155119ed80c29f1": {
      "id": "track-2155119ed80c29f1",
      "title": "BLAHBLAHBLAH DEMO",
      "artist": "Joji",
      "album": "SMITHEREENS",
      "duration": 0,
      "file_path": "/home/jscyril/Music/FLAC/complete/SMITHEREENS-1/2-02 BLAHBLAHBLAH DEMO.mp3",
      "genre": "AlternativeDowntempoElectronicPopAlternative pop",
      "year": 2022,
      "track_number": 7,
      "created_at": "2026-01-28T16:20:22.460689416+05:30"
    },
    "track-221ed5140d44f4e4": {
      "id": "track-221ed5140d44f4e4",
      "title": "Gimme Love",
      "artist": "Joji",
      "album": "Nectar",
      "duration": 0,
      "file_path": "/home/jscyril/Music/FLAC/complete/Nectar/Joji_Nectar_06_Gimme Love.flac",
      "genre": "",
      "year": 2020,
      "track_number": 6,
      "created_at": "2026-01-28T16:20:22.450891658+05:30"
    },
    "track-226af6cc8c97c737": {
      "id": "track-226af6cc8c97c737",
      "title": "The Color Violet",
      "artist": "Tory Lanez",
      "album": "Alone At Prom",
      "duration": 0,
      "file_path": "/home/jscyril/Music/FLAC/complete/Tory Lanez - The Color Violet.flac",
      "genre": "",
      "year": 2021,
      "track_number": 0,
      "created_at": "2026-01-28T16:20:22.462342758+05:30"
    },
    "track-24246f17074301c2": {
      "id": "track-24246f17074301c2",
      "title": "Mirror (Feat. Bruno Mars)",
      "artist": "Lil Wayne",
      "album": "Top 100 Van 2012",
      "duration": 0,
      "file_path": "/home/jscyril/Music/FLAC/complete/Top 100 Van 2012/068 - Lil Wayne - Mirror (Feat. Bruno Mars).flac",
      "genre": "Top 40",
      "year": 2012,
      "track_number": 68,
      "created_at": "2026-01-28T16:20:22.461370153+05:30"
    },
    "track-25799907a003b95c": {
      "id": "track-25799907a003b95c",
      "title": "Be Yourself",
      "artist": "Frank Ocean",
      "album": "Blonde",
      "duration": 0,
      "file_path": "/home/jscyril/Music/FLAC/complete/transon/2016 - Blonde/04. Be Yourself.flac",
      "genre": "Art Pop; Pop; Rnb; Soul",
      "year": 2016,
      "track_number": 4,
      "created_at": "2026-01-28T16:20:22.466597418+05:30"
    },
    "track-29a9456f693ca4cc": {
      "id": "track-29a9456f693ca4cc",
      "title": "Before the Day Is Over",
      "artist": "Joji",
      "album": "SMITHEREENS",
      "duration": 0,
      "file_path": "/home/jscyril/Music/FLAC/complete/SMITHEREENS-1/1-04 Before the Day Is Over.mp3",
      "genre": "AlternativeDowntempoElectronicPopAlternative pop",
      "year": 2022,
      "track_number": 4,
      "created_at": "2026-01-28T16:20:22.458836811+05:30"
    },
    "track-2a12b11737cd556a": {
      "id": "track-2a12b11737cd556a",
      "title": "Solo",
      "artist": "Frank Ocean",
      "album": "Blonde",
      "duration": 0,
      "file_path": "/home/jscyril/Music/FLAC/complete/transon/2016 - Blonde/05. Solo.flac",
      "genre": "Art Pop; Pop; Rnb; Soul",
      "year": 2016,
      "track_number": 5,
      "created_at": "2026-01-28T16:20:22.466610543+05:30"
    },
    "track-2b5ff71c2e9f8576": {
      "id": "track-2b5ff71c2e9f8576",
      "title": "Nikes",
      "artist": "Frank Ocean",
      "album": "Blonde",
      "duration": 0,
      "file_path": "/home/jscyril/Music/FLAC/complete/transon/2016 - Blonde/01. Nikes.flac",
      "genre": "Art Pop; Pop; Rnb; Soul",
      "year": 2016,
      "track_number": 1,
      "created_at": "2026-01-28T16:20:22.464891058+05:30"
    },
    "track-2d6cebda42da4758": {
      "id": "track-2d6cebda42da4758",
      "title": "Rain",
      "artist": "Adrián Berenguer",
      "album": "Immaterial",
      "duration": 0,
      "file_path": "/home/jscyril/Music/FLAC/complete/Adrián Berenguer - Rain.flac",
      "genre": "",
      "year": 2021,
      "track_number": 0,
      "created_at": "2026-01-28T16:20:22.432843595+05:30"
    },
    "track-2dd9e718bb647422": {
      "id": "track-2dd9e718bb647422",
      "title": "Afterthought",
      "artist": "Joji \u0026 BENEE",
      "album": "Nectar",
      "duration": 0,
      "file_path": "/home/jscyril/Music/FLAC/complete/Nectar/Joji_Nectar_13_Afterthought.flac",
      "genre": "",
      "year": 2020,
      "track_number": 13,
      "created_at": "2026-01-28T16:20:22.454030736+05:30"
    },
    "track-316b9065c5e79586": {
      "id": "track-316b9065c5e79586",
      "title": "Your Man",
      "artist": "Joji",
      "album": "Nectar",
      "duration": 0,
      "file_path": "/home/jscyril/Music/FLAC/complete/Nectar/Joji_Nectar_18_Your Man.flac",
      "genre": "",
      "year": 2020,
      "track_number": 18,
      "created_at": "2026-01-28T16:20:22.456619472+05:30"
    },
    "track-324184b6dedc2456": {
      "id": "track-324184b6dedc2456",
      "title": "MY EYES",
      "artist": "Travis Scott",
      "album": "UTOPIA",
      "duration": 0,
      "file_path": "/home/jscyril/Music/FLAC/complete/UTOPIA (2023)/Travis Scott - UTOPIA - 04 - MY EYES.flac",
      "genre": "Hip-Hop/Rap",
      "year": 1,
      "track_number": 4,
      "created_at": "2026-01-28T16:20:22.462992657+05:30"
    },
    "track-35c5b50d7dd3d3c8": {
      "id": "track-35c5b50d7dd3d3c8",
      "title": "Destroyer Of Worlds",
      "artist": "Ludwig Goransson",
      "album": "Oppenheimer (Original Motion Picture Soundtrack)",
      "duration": 0,
      "file_path": "/home/jscyril/Music/FLAC/complete/Ludwig Goransson - Destroyer Of Worlds.flac",
      "genre": "",
      "year": 2023,
      "track_number": 0,
      "created_at": "2026-01-28T16:20:22.446360239+05:30"
    },
    "track-37dc59b3bc807f25": {
      "id": "track-37dc59b3bc807f25",
      "title": "I'll See You in 40",
      "artist": "Joji",
      "album": "BALLADS 1",
      "duration": 0,
      "file_path": "/home/jscyril/Music/FLAC/complete/BALLADS 1/Joji_BALLADS 1_12_I’LL SEE YOU IN 40.flac",
      "genre": "R\u0026B",
      "year": 2018,
      "track_number": 12,
      "created_at": "2026-01-28T16:20:22.441325835+05:30"
    },
    "track-3b791e1b20d0a8b4": {
      "id": "track-3b791e1b20d0a8b4",
      "title": "Die for You",
      "artist": "Joji",
      "album": "SMITHEREENS",
      "duration": 0,
      "file_path": "/home/jscyril/Music/FLAC/complete/SMITHEREENS-1/1-03 Die for You.mp3",
      "genre": "AlternativeDowntempoElectronicPopAlternative pop",
      "year": 2022,
      "track_number": 3,
      "created_at": "2026-01-28T16:20:22.45851635+05:30"
    },
    "track-3c56b00ec6b820ea": {
      "id": "track-3c56b00ec6b820ea",
      "title": "To Ashes and Blood",
      "artist": "Woodkid",
      "album": "Arcane League of Legends: Season 2 (Soundtrack from the Animated Series)",
      "duration": 0,
      "file_path": "/home/jscyril/Music/FLAC/complete/Arcane League of Legends  Season 2 (Soundtrack from the Animated Series)/1-06 - To Ashes and Blood.flac",
      "genre": "Soundtrack",
      "year": 2024,
      "track_number": 6,
      "created_at": "2026-01-28T16:20:22.434819802+05:30"
    },
    "track-3f986a9b722a5846": {
      "id": "track-3f986a9b722a5846",
      "title": "Dissolve",
      "artist": "Joji",
      "album": "SMITHEREENS",
      "duration": 0,
      "file_path": "/home/jscyril/Music/FLAC/complete/SMITHEREENS-1/1-05 Dissolve.mp3",
      "genre": "AlternativeDowntempoElectronicPopAlternative pop",
      "year": 2022,
      "track_number": 5,
      "created_at": "2026-01-28T16:20:22.459446695+05:30"
    },
    "track-4089ba6eebd25a48": {
      "id": "track-4089ba6eebd25a48",
      "title": "Superhero (Heroes \u0026 Villains)",
      "artist": "Metro Boomin",
      "album": "HEROES \u0026 VILLAINS",
      "duration": 0,
      "file_path": "/home/jscyril/Music/FLAC/complete/Metro Boomin - Superhero (Heroes \u0026 Villains).flac",
      "genre": "",
      "year": 2022,
      "track_number": 0,
      "created_at": "2026-01-28T16:20:22.447579566+05:30"
    },
    "track-412d56b1192224c0": {
      "id": "track-412d56b1192224c0",
      "title": "Close to You",
      "artist": "Frank Ocean",
      "album": "Blonde",
      "duration": 0,
      "file_path": "/home/jscyril/Music/FLAC/complete/transon/2016 - Blonde/13. Close to You.flac",
      "genre": "Art Pop; Pop; Rnb; Soul",
      "year": 2016,
      "track_number": 13,
      "created_at": "2026-01-28T16:20:22.470844174+05:30"
    },
    "track-43b2dbdd91c7ffbe": {
      "id": "track-43b2dbdd91c7ffbe",
      "title": "Godspeed",
      "artist": "Frank Ocean",
      "album": "Blonde",
      "duration": 0,
      "file_path": "/home/jscyril/Music/FLAC/complete/transon/2016 - Blonde/16. Godspeed.flac",
      "genre": "Art Pop; Pop; Rnb; Soul",
      "year": 2016,
      "track_number": 16,
      "created_at": "2026-01-28T16:20:22.471915544+05:30"
    },
    "track-455f45583a899f1c": {
      "id": "track-455f45583a899f1c",
      "title": "XNXX",
      "artist": "Joji",
      "album": "BALLADS 1",
      "duration": 0,
      "file_path": "/home/jscyril/Music/FLAC/complete/BALLADS 1/Joji_BALLADS 1_11_XNXX.flac",
      "genre": "R\u0026B",
      "year": 2018,
      "track_number": 11,
      "created_at": "2026-01-28T16:20:22.441258669+05:30"
    },
    "track-4633536aa55502ab": {
      "id": "track-4633536aa55502ab",
      "title": "YUKON (INTERLUDE)",
      "artist": "Joji",
      "album": "SMITHEREENS",
      "duration": 0,
      "file_path": "/home/jscyril/Music/FLAC/complete/SMITHEREENS-1/2-03 YUKON (INTERLUDE).mp3",
      "genre": "AlternativeDowntempoElectronicPopAlternative pop",
      "year": 2022,
      "track_number": 8,
      "created_at": "2026-01-28T16:20:22.460885404+05:30"
    },
    "track-480dc5f2a17a6bf5": {
      "id": "track-480dc5f2a17a6bf5",
      "title": "Free Bird",
      "artist": "Lynyrd Skynyrd",
      "album": "(Pronounced 'Lĕh-'nérd 'Skin-'nérd)",
      "duration": 0,
      "file_path": "/home/jscyril/Music/FLAC/complete/(Pronounced 'Lĕh-'nérd 'Skin-'nérd)/08 - Free Bird.flac",
      "genre": "Rock",
      "year": 2014,
      "track_number": 8,
      "created_at": "2026-01-28T16:20:22.434346744+05:30"
    },
    "track-54be231af5889629": {
      "id": "track-54be231af5889629",
      "title": "Remember Me (intro)",
      "artist": "d4vd",
      "album": "Arcane League of Legends: Season 2 (Soundtrack from the Animated Series)",
      "duration": 0,
      "file_path": "/home/jscyril/Music/FLAC/complete/Arcane League of Legends  Season 2 (Soundtrack from the Animated Series)/1-08 - Remember Me (intro).flac",
      "genre": "Soundtrack",
      "year": 2024,
      "track_number": 8,
      "created_at": "2026-01-28T16:20:22.435337362+05:30"
    },
    "track-58d93cb45ff01a53": {
      "id": "track-58d93cb45ff01a53",
      "title": "Good Guy",
      "artist": "Frank Ocean",
      "album": "Blonde",
      "duration": 0,
      "file_path": "/home/jscyril/Music/FLAC/complete/transon/2016 - Blonde/08. Good Guy.flac",
      "genre": "Art Pop; Pop; Rnb; Soul",
      "year": 2016,
      "track_number": 8,
      "created_at": "2026-01-28T16:20:22.467915451+05:30"
    },
    "track-59dcfee8c55b6be0": {
      "id": "track-59dcfee8c55b6be0",
      "title": "The Line (from the series Arcane League of Legends)",
      "artist": "twenty one pilots",
      "album": "Arcane League of Legends: Season 2 (Soundtrack from the Animated Series)",
      "duration": 0,
      "file_path": "/home/jscyril/Music/FLAC/complete/Arcane League of Legends - Soundtrack from the Animated Series [Season 2]/18. Twenty One Pilots - The Line (from the series Arcane League of Legends).flac",
      "genre": "",
      "year": 2024,
      "track_number": 18,
      "created_at": "2026-01-28T16:20:22.436422919+05:30"
    },
    "track-5c60ace4aab00385": {
      "id": "track-5c60ace4aab00385",
      "title": "White Ferrari",
      "artist": "Frank Ocean",
      "album": "Blonde",
      "duration": 0,
      "file_path": "/home/jscyril/Music/FLAC/complete/transon/2016 - Blonde/14. White Ferrari.flac",
      "genre": "Art Pop; Pop; Rnb; Soul",
      "year": 2016,
      "track_number": 14,
      "created_at": "2026-01-28T16:20:22.471239877+05:30"
    },
    "track-62859985801c8805": {
      "id": "track-62859985801c8805",
      "title": "1AM FREESTYLE",
      "artist": "Joji",
      "album": "SMITHEREENS",
      "duration": 0,
      "file_path": "/home/jscyril/Music/FLAC/complete/SMITHEREENS-1/2-04 1AM FREESTYLE.mp3",
      "genre": "AlternativeDowntempoElectronicPopAlternative pop",
      "year": 2022,
      "track_number": 9,
      "created_at": "2026-01-28T16:20:22.461511478+05:30"
    },
    "track-67985ff234c64842": {
      "id": "track-67985ff234c64842",
      "title": "Mr. Hollywood",
      "artist": "Joji",
      "album": "Nectar",
      "duration": 0,
      "file_path": "/home/jscyril/Music/FLAC/complete/Nectar/Joji_Nectar_14_Mr. Hollywood.flac",
      "genre": "",
      "year": 2020,
      "track_number": 14,
      "created_at": "2026-01-28T16:20:22.454508473+05:30"
    },
    "track-69ea3d0c65511f52": {
      "id": "track-69ea3d0c65511f52",
      "title": "The Plan",
      "artist": "Travis Scott",
      "album": "The Plan (From the Motion Picture \"TENET\")",
      "duration": 0,
      "file_path": "/home/jscyril/Music/FLAC/complete/Travis Scott - The Plan.flac",
      "genre": "",
      "year": 2020,
      "track_number": 0,
      "created_at": "2026-01-28T16:20:22.461867707+05:30"
    },
    "track-69f9e85c15d6307a": {
      "id": "track-69f9e85c15d6307a",
      "title": "MODUS",
      "artist": "Joji",
      "album": "Nectar",
      "duration": 0,
      "file_path": "/home/jscyril/Music/FLAC/complete/Nectar/Joji_Nectar_02_MODUS.flac",
      "genre": "",
      "year": 2020,
      "track_number": 2,
      "created_at": "2026-01-28T16:20:22.448564513+05:30"
    },
    "track-6b0fc3d732ae148d": {
      "id": "track-6b0fc3d732ae148d",
      "title": "Too Many Nights",
      "artist": "Metro Boomin",
      "album": "HEROES \u0026 VILLAINS",
      "duration": 0,
      "file_path": "/home/jscyril/Music/FLAC/complete/Metro Boomin - Too Many Nights.flac",
      "genre": "",
      "year": 2022,
      "track_number": 0,
      "created_at": "2026-01-28T16:20:22.447931756+05:30"
    },
    "track-7034e80d27c55ea0": {
      "id": "track-7034e80d27c55ea0",
      "title": "Wake Me Up",
      "artist": "Avicii",
      "album": "True",
      "duration": 0,
      "file_path": "/home/jscyril/Music/FLAC/complete/Avicii - Wake Me Up.flac",
      "genre": "",
      "year": 2013,
      "track_number": 0,
      "created_at": "2026-01-28T16:20:22.439141488+05:30"
    },
    "track-74363d0881ddea7d": {
      "id": "track-74363d0881ddea7d",
      "title": "Reanimator (feat. Yves Tumor)",
      "artist": "Joji",
      "album": "Nectar",
      "duration": 0,
      "file_path": "/home/jscyril/Music/FLAC/complete/Nectar/Joji_Nectar_16_Reanimator.flac",
      "genre": "",
      "year": 2020,
      "track_number": 16,
      "created_at": "2026-01-28T16:20:22.455395847+05:30"
    },
    "track-76630a374e084f9a": {
      "id": "track-76630a374e084f9a",
      "title": "Upgrade",
      "artist": "Joji",
      "album": "Nectar",
      "duration": 0,
      "file_path": "/home/jscyril/Music/FLAC/complete/Nectar/Joji_Nectar_05_Upgrade.flac",
      "genre": "",
      "year": 2020,
      "track_number": 5,
      "created_at": "2026-01-28T16:20:22.45007678+05:30"
    },
    "track-788511ea3469834a": {
      "id": "track-788511ea3469834a",
      "title": "The Nights",
      "artist": "Avicii",
      "album": "The Days / Nights (EP)",
      "duration": 0,
      "file_path": "/home/jscyril/Music/FLAC/complete/Avicii - The Nights.flac",
      "genre": "",
      "year": 2014,
      "track_number": 0,
      "created_at": "2026-01-28T16:20:22.439279637+05:30"
    },
    "track-7c225476a3de260b": {
      "id": "track-7c225476a3de260b",
      "title": "Skyline To",
      "artist": "Frank Ocean",
      "album": "Blonde",
      "duration": 0,
      "file_path": "/home/jscyril/Music/FLAC/complete/transon/2016 - Blonde/06. Skyline To.flac",
      "genre": "Art Pop; Pop; Rnb; Soul",
      "year": 2016,
      "track_number": 6,
      "created_at": "2026-01-28T16:20:22.467567779+05:30"
    },
    "track-7d94bbed63ac4260": {
      "id": "track-7d94bbed63ac4260",
      "title": "From the Start",
      "artist": "Laufey",
      "album": "Bewitched: The Goddess Edition",
      "duration": 0,
      "file_path": "/home/jscyril/Music/FLAC/complete/Unwrapped3759/Bewitched_ The Goddess Edition/10 Laufey - From the Start.flac",
      "genre": "Jazz",
      "year": 2024,
      "track_number": 10,
      "created_at": "2026-01-28T16:20:22.463057699+05:30"
    },
    "track-80dce6b3611e2cf0": {
      "id": "track-80dce6b3611e2cf0",
      "title": "Ew",
      "artist": "Joji",
      "album": "Nectar",
      "duration": 0,
      "file_path": "/home/jscyril/Music/FLAC/complete/Nectar/Joji_Nectar_01_Ew.flac",
      "genre": "",
      "year": 2020,
      "track_number": 1,
      "created_at": "2026-01-28T16:20:22.448735614+05:30"
    },
    "track-82ae3fa2b568eb98": {
      "id": "track-82ae3fa2b568eb98",
      "title": "777",
      "artist": "Joji",
      "album": "Nectar",
      "duration": 0,
      "file_path": "/home/jscyril/Music/FLAC/complete/Nectar/Joji_Nectar_15_777.flac",
      "genre": "",
      "year": 2020,
      "track_number": 15,
      "created_at": "2026-01-28T16:20:22.455379046+05:30"
    },
    "track-88230938ced05394": {
      "id": "track-88230938ced05394",
      "title": "a m a r i",
      "artist": "J. Cole",
      "album": "The Off-Season",
      "duration": 0,
      "file_path": "/home/jscyril/Music/FLAC/complete/J. Cole - a m a r i.flac",
      "genre": "",
      "year": 2021,
      "track_number": 0,
      "created_at": "2026-01-28T16:20:22.44517237+05:30"
    },
    "track-88a27aa11ac7b468": {
      "id": "track-88a27aa11ac7b468",
      "title": "I'd Rather Pretend",
      "artist": "Bryant Barnes",
      "album": "I'd Rather Pretend",
      "duration": 0,
      "file_path": "/home/jscyril/Music/FLAC/complete/soulshookt/Bryant Barnes \u0026 d4vd - I'd Rather Pretend (FLAC) [24-Bit 44.1-kHz]/01. I'd Rather Pretend.flac",
      "genre": "Alternative",
      "year": 2024,
      "track_number": 1,
      "created_at": "2026-01-28T16:20:22.463480201+05:30"
    },
    "track-8b2e71f3c04ce2c3": {
      "id": "track-8b2e71f3c04ce2c3",
      "title": "LOVELY BASTARDS",
      "artist": "ZWE1HVNDXR, yatashigang",
      "album": "LOVELY BASTARDS",
      "duration": 0,
      "file_path": "/home/jscyril/Music/FLAC/complete/The Official UK Top 100 Singles Chart (14-September-2023) Mp3 320kbps [PMEDIA] ⭐️/096. ZWE1HVNDXR - LOVELY BASTARDS.mp3",
      "genre": "Electro",
      "year": 2023,
      "track_number": 96,
      "created_at": "2026-01-28T16:20:22.462853265+05:30"
    },
    "track-8b6b417d6e6c89ba": {
      "id": "track-8b6b417d6e6c89ba",
      "title": "Pretty Sweet",
      "artist": "Frank Ocean",
      "album": "Blonde",
      "duration": 0,
      "file_path": "/home/jscyril/Music/FLAC/complete/transon/2016 - Blonde/11. Pretty Sweet.flac",
      "genre": "Art Pop; Pop; Rnb; Soul",
      "year": 2016,
      "track_number": 11,
      "created_at": "2026-01-28T16:20:22.471026436+05:30"
    },
    "track-9081014dbd9330db": {
      "id": "track-9081014dbd9330db",
      "title": "Past Lives",
      "artist": "Farizki",
      "album": "Past Lives",
      "duration": 0,
      "file_path": "/home/jscyril/Music/FLAC/complete/Farizki - Past Lives.flac",
      "genre": "",
      "year": 2022,
      "track_number": 0,
      "created_at": "2026-01-28T16:20:22.444528593+05:30"
    },
    "track-935a5b6493961afd": {
      "id": "track-935a5b6493961afd",
      "title": "luther (feat. SZA)",
      "artist": "Kendrick Lamar, SZA",
      "album": "GNX",
      "duration": 0,
      "file_path": "/home/jscyril/Music/FLAC/complete/TurtleMasterVIIX/GNX/03 luther (feat. SZA).flac",
      "genre": "Hip-Hop/ Rap",
      "year": 2024,
      "track_number": 3,
      "created_at": "2026-01-28T16:20:22.468456546+05:30"
    },
    "track-93967b344615b2f4": {
      "id": "track-93967b344615b2f4",
      "title": "Tick Tock",
      "artist": "Joji",
      "album": "Nectar",
      "duration": 0,
      "file_path": "/home/jscyril/Music/FLAC/complete/Nectar/Joji_Nectar_03_Tick Tock.flac",
      "genre": "",
      "year": 2020,
      "track_number": 3,
      "created_at": "2026-01-28T16:20:22.449406553+05:30"
    },
    "track-96e9672075ea91f7": {
      "id": "track-96e9672075ea91f7",
      "title": "PIXELATED KISSES",
      "artist": "Joji",
      "album": "PIXELATED KISSES",
      "duration": 0,
      "file_path": "/home/jscyril/Music/FLAC/complete/Joji - PIXELATED KISSES.flac",
      "genre": "",
      "year": 2025,
      "track_number": 0,
      "created_at": "2026-01-28T16:20:22.447406+05:30"
    },
    "track-97872edadab90baa": {
      "id": "track-97872edadab90baa",
      "title": "No Idea",
      "artist": "Don Toliver",
      "album": "Heaven Or Hell",
      "duration": 0,
      "file_path": "/home/jscyril/Music/FLAC/complete/Don Toliver - No Idea.flac",
      "genre": "",
      "year": 2019,
      "track_number": 0,
      "created_at": "2026-01-28T16:20:22.442700624+05:30"
    },
    "track-9b6492074b00e881": {
      "id": "track-9b6492074b00e881",
      "title": "Fair Trade",
      "artist": "Drake",
      "album": "Certified Lover Boy",
      "duration": 0,
      "file_path": "/home/jscyril/Music/FLAC/complete/Drake - Fair Trade.flac",
      "genre": "",
      "year": 2021,
      "track_number": 0,
      "created_at": "2026-01-28T16:20:22.442543319+05:30"
    },
    "track-9bbbfc798c92f0cd": {
      "id": "track-9bbbfc798c92f0cd",
      "title": "NIGHT RIDER",
      "artist": "Joji",
      "album": "SMITHEREENS",
      "duration": 0,
      "file_path": "/home/jscyril/Music/FLAC/complete/SMITHEREENS-1/2-01 NIGHT RIDER.mp3",
      "genre": "AlternativeDowntempoElectronicPopAlternative pop",
      "year": 2022,
      "track_number": 6,
      "created_at": "2026-01-28T16:20:22.460546679+05:30"
    },
    "track-9cc5b013743cdab8": {
      "id": "track-9cc5b013743cdab8",
      "title": "Seigfried",
      "artist": "Frank Ocean",
      "album": "Blonde",
      "duration": 0,
      "file_path": "/home/jscyril/Music/FLAC/complete/transon/2016 - Blonde/15. Seigfried.flac",
      "genre": "Art Pop; Pop; Rnb; Soul",
      "year": 2016,
      "track_number": 15,
      "created_at": "2026-01-28T16:20:22.471644986+05:30"
    },
    "track-9d7a272634342113": {
      "id": "track-9d7a272634342113",
      "title": "Like You Do",
      "artist": "Joji",
      "album": "Nectar",
      "duration": 0,
      "file_path": "/home/jscyril/Music/FLAC/complete/Nectar/Joji_Nectar_17_Like You Do.flac",
      "genre": "",
      "year": 2020,
      "track_number": 17,
      "created_at": "2026-01-28T16:20:22.455478532+05:30"
    },
    "track-a1ae4cb97a308146": {
      "id": "track-a1ae4cb97a308146",
      "title": "Attention",
      "artist": "Joji",
      "album": "BALLADS 1",
      "duration": 0,
      "file_path": "/home/jscyril/Music/FLAC/complete/BALLADS 1/Joji_BALLADS 1_01_ATTENTION.flac",
      "genre": "R\u0026B",
      "year": 2018,
      "track_number": 1,
      "created_at": "2026-01-28T16:20:22.439413358+05:30"
    },
    "track-a4b16b7679c4ff3b": {
      "id": "track-a4b16b7679c4ff3b",
      "title": "NITROUS",
      "artist": "Joji",
      "album": "Nectar",
      "duration": 0,
      "file_path": "/home/jscyril/Music/FLAC/complete/Nectar/Joji_Nectar_10_NITROUS.flac",
      "genre": "",
      "year": 2020,
      "track_number": 10,
      "created_at": "2026-01-28T16:20:22.452277939+05:30"
    },
    "track-a6a219bd292ee2fd": {
      "id": "track-a6a219bd292ee2fd",
      "title": "Sky",
      "artist": "Playboi Carti",
      "album": "Whole Lotta Red",
      "duration": 0,
      "file_path": "/home/jscyril/Music/FLAC/complete/Playboi Carti - Sky.flac",
      "genre": "",
      "year": 2020,
      "track_number": 0,
      "created_at": "2026-01-28T16:20:22.456105318+05:30"
    },
    "track-af1968844a27be69": {
      "id": "track-af1968844a27be69",
      "title": "Run",
      "artist": "Joji",
      "album": "Nectar",
      "duration": 0,
      "file_path": "/home/jscyril/Music/FLAC/complete/Nectar/Joji_Nectar_07_Run.flac",
      "genre": "",
      "year": 2020,
      "track_number": 7,
      "created_at": "2026-01-28T16:20:22.450983671+05:30"
    },
    "track-b14a6a87014727a5": {
      "id": "track-b14a6a87014727a5",
      "title": "Solo (reprise)",
      "artist": "Frank Ocean",
      "album": "Blonde",
      "duration": 0,
      "file_path": "/home/jscyril/Music/FLAC/complete/transon/2016 - Blonde/10. Solo (reprise).flac",
      "genre": "Art Pop; Pop; Rnb; Soul",
      "year": 2016,
      "track_number": 10,
      "created_at": "2026-01-28T16:20:22.470072156+05:30"
    },
    "track-b19e8f6bc1431409": {
      "id": "track-b19e8f6bc1431409",
      "title": "Pink + White",
      "artist": "Frank Ocean",
      "album": "Blonde",
      "duration": 0,
      "file_path": "/home/jscyril/Music/FLAC/complete/Frank Ocean - Pink + White.flac",
      "genre": "Soul",
      "year": 2016,
      "track_number": 0,
      "created_at": "2026-01-28T16:20:22.444677582+05:30"
    },
    "track-b271ab8da3baa8f5": {
      "id": "track-b271ab8da3baa8f5",
      "title": "See You Again",
      "artist": "Tyler, the Creator feat. Kali Uchis",
      "album": "Flower Boy",
      "duration": 0,
      "file_path": "/home/jscyril/Music/FLAC/complete/2017 - Flower Boy/04 - See You Again.flac",
      "genre": "Hip-Hop",
      "year": 2017,
      "track_number": 4,
      "created_at": "2026-01-28T16:20:22.441922504+05:30"
    },
    "track-b3b173f6994b37ba": {
      "id": "track-b3b173f6994b37ba",
      "title": "Slow Dancing in the Dark",
      "artist": "Joji",
      "album": "BALLADS 1",
      "duration": 0,
      "file_path": "/home/jscyril/Music/FLAC/complete/BALLADS 1/Joji_BALLADS 1_02_SLOW DANCING IN THE DARK.flac",
      "genre": "R\u0026B",
      "year": 2018,
      "track_number": 2,
      "created_at": "2026-01-28T16:20:22.439988417+05:30"
    },
    "track-b5b488cca39b4d22": {
      "id": "track-b5b488cca39b4d22",
      "title": "Am I Dreaming",
      "artist": "Metro Boomin",
      "album": "METRO BOOMIN PRESENTS SPIDER-MAN: ACROSS THE SPIDER-VERSE (SOUNDTRACK FROM AND INSPIRED BY THE MOTION PICTURE)",
      "duration": 0,
      "file_path": "/home/jscyril/Music/FLAC/complete/Metro Boomin - Am I Dreaming.flac",
      "genre": "",
      "year": 2023,
      "track_number": 0,
      "created_at": "2026-01-28T16:20:22.447449271+05:30"
    },
    "track-bdba55746ddc16a5": {
      "id": "track-bdba55746ddc16a5",
      "title": "Miss The Rage",
      "artist": "Trippie Redd",
      "album": "Miss The Rage",
      "duration": 0,
      "file_path": "/home/jscyril/Music/FLAC/complete/Trippie Redd - Miss The Rage.flac",
      "genre": "",
      "year": 2021,
      "track_number": 0,
      "created_at": "2026-01-28T16:20:22.461763441+05:30"
    },
    "track-be9055ae83057126": {
      "id": "track-be9055ae83057126",
      "title": "Normal People (feat. rei brown)",
      "artist": "Joji",
      "album": "Nectar",
      "duration": 0,
      "file_path": "/home/jscyril/Music/FLAC/complete/Nectar/Joji_Nectar_12_Normal People.flac",
      "genre": "",
      "year": 2020,
      "track_number": 12,
      "created_at": "2026-01-28T16:20:22.454204913+05:30"
    },
    "track-c058ceba72591ef5": {
      "id": "track-c058ceba72591ef5",
      "title": "Thousands of Summer Twilights",
      "artist": "Owsey",
      "album": "Thousands of Summer Twilights",
      "duration": 0,
      "file_path": "/home/jscyril/Music/FLAC/complete/Owsey - Thousands of Summer Twilights.flac",
      "genre": "",
      "year": 2019,
      "track_number": 0,
      "created_at": "2026-01-28T16:20:22.456217348+05:30"
    },
    "track-c53976f7e6f923ce": {
      "id": "track-c53976f7e6f923ce",
      "title": "Feeling Like the End",
      "artist": "Joji",
      "album": "SMITHEREENS",
      "duration": 0,
      "file_path": "/home/jscyril/Music/FLAC/complete/SMITHEREENS-1/1-02 Feeling Like the End.mp3",
      "genre": "AlternativeDowntempoElectronicPopAlternative pop",
      "year": 2022,
      "track_number": 2,
      "created_at": "2026-01-28T16:20:22.458299714+05:30"
    },
    "track-c5f93c88f5b52a3d": {
      "id": "track-c5f93c88f5b52a3d",
      "title": "No Fun",
      "artist": "Joji",
      "album": "BALLADS 1",
      "duration": 0,
      "file_path": "/home/jscyril/Music/FLAC/complete/BALLADS 1/Joji_BALLADS 1_08_NO FUN.flac",
      "genre": "R\u0026B",
      "year": 2018,
      "track_number": 8,
      "created_at": "2026-01-28T16:20:22.440907771+05:30"
    },
    "track-c8aaad83d0aa20d2": {
      "id": "track-c8aaad83d0aa20d2",
      "title": "Wasteland (from the series Arcane League of Legends)",
      "artist": "Royal \u0026 The Serpent",
      "album": "Arcane League of Legends: Season 2 (Soundtrack from the Animated Series)",
      "duration": 0,
      "file_path": "/home/jscyril/Music/FLAC/complete/Arcane League of Legends Season 2 (Soundtrack from the Animated Series)/Royal \u0026 The Serpent  - Wasteland (from the series Arcane League of Legends).flac",
      "genre": "Pop",
      "year": 2024,
      "track_number": 21,
      "created_at": "2026-01-28T16:20:22.440453188+05:30"
    },
    "track-cae63e0242dcfded": {
      "id": "track-cae63e0242dcfded",
      "title": "Pink + White",
      "artist": "Frank Ocean",
      "album": "Blonde",
      "duration": 0,
      "file_path": "/home/jscyril/Music/FLAC/complete/transon/2016 - Blonde/03. Pink + White.flac",
      "genre": "Art Pop; Pop; Rnb; Soul",
      "year": 2016,
      "track_number": 3,
      "created_at": "2026-01-28T16:20:22.465679346+05:30"
    },
    "track-cc343ba55e97d98d": {
      "id": "track-cc343ba55e97d98d",
      "title": "Strangers",
      "artist": "Kenya Grace",
      "album": "Strangers",
      "duration": 0,
      "file_path": "/home/jscyril/Music/FLAC/complete/Singles 2023-09-01/Kenya Grace - Strangers.flac",
      "genre": "",
      "year": 2023,
      "track_number": 0,
      "created_at": "2026-01-28T16:20:22.46136814+05:30"
    },
    "track-d2d0e8d170dec218": {
      "id": "track-d2d0e8d170dec218",
      "title": "Come Thru",
      "artist": "Joji",
      "album": "BALLADS 1",
      "duration": 0,
      "file_path": "/home/jscyril/Music/FLAC/complete/BALLADS 1/Joji_BALLADS 1_09_COME THRU.flac",
      "genre": "R\u0026B",
      "year": 2018,
      "track_number": 9,
      "created_at": "2026-01-28T16:20:22.440846045+05:30"
    },
    "track-d3dd84966b5aaa0b": {
      "id": "track-d3dd84966b5aaa0b",
      "title": "I Love It (Feat. Charli XCX)",
      "artist": "Icona Pop",
      "album": "This Is...",
      "duration": 0,
      "file_path": "/home/jscyril/Music/FLAC/complete/01-icona_pop-i_love_it_(feat._charli_xcx).flac",
      "genre": "Pop",
      "year": 2013,
      "track_number": 1,
      "created_at": "2026-01-28T16:20:22.432327687+05:30"
    },
    "track-d553d9125f487b65": {
      "id": "track-d553d9125f487b65",
      "title": "All The Way Live",
      "artist": "Metro Boomin",
      "album": "METRO BOOMIN PRESENTS SPIDER-MAN: ACROSS THE SPIDER-VERSE (SOUNDTRACK FROM AND INSPIRED BY THE MOTION PICTURE)",
      "duration": 0,
      "file_path": "/home/jscyril/Music/FLAC/complete/Metro Boomin - All The Way Live.flac",
      "genre": "",
      "year": 2023,
      "track_number": 0,
      "created_at": "2026-01-28T16:20:22.446960605+05:30"
    },
    "track-d55c37b8361075fe": {
      "id": "track-d55c37b8361075fe",
      "title": "Ivy",
      "artist": "Frank Ocean",
      "album": "Blonde",
      "duration": 0,
      "file_path": "/home/jscyril/Music/FLAC/complete/transon/2016 - Blonde/02. Ivy.flac",
      "genre": "Art Pop; Pop; Rnb; Soul",
      "year": 2016,
      "track_number": 2,
      "created_at": "2026-01-28T16:20:22.465204686+05:30"
    },
    "track-d567ec69280ec3b0": {
      "id": "track-d567ec69280ec3b0",
      "title": "Daylight",
      "artist": "David Kushner",
      "album": "Daylight",
      "duration": 0,
      "file_path": "/home/jscyril/Music/FLAC/complete/David Kushner - Daylight.flac",
      "genre": "",
      "year": 2023,
      "track_number": 0,
      "created_at": "2026-01-28T16:20:22.442558588+05:30"
    },
    "track-ddbe9ec7d4ed59bd": {
      "id": "track-ddbe9ec7d4ed59bd",
      "title": "Self Control",
      "artist": "Frank Ocean",
      "album": "Blonde",
      "duration": 0,
      "file_path": "/home/jscyril/Music/FLAC/complete/transon/2016 - Blonde/07. Self Control.flac",
      "genre": "Art Pop; Pop; Rnb; Soul",
      "year": 2016,
      "track_number": 7,
      "created_at": "2026-01-28T16:20:22.468488055+05:30"
    },
    "track-ddbf520f5866816a": {
      "id": "track-ddbf520f5866816a",
      "title": "Renegade (We Never Run)",
      "artist": "Raja Kumari, Stefflon Don \u0026 Jarina De Marco",
      "album": "Arcane League of Legends: Season 2 (Soundtrack from the Animated Series)",
      "duration": 0,
      "file_path": "/home/jscyril/Music/FLAC/complete/Arcane League of Legends  Season 2 (Soundtrack from the Animated Series)/1-04 - Renegade (We Never Run).flac",
      "genre": "Soundtrack",
      "year": 2024,
      "track_number": 4,
      "created_at": "2026-01-28T16:20:22.434785998+05:30"
    },
    "track-de2158afa1b5cd53": {
      "id": "track-de2158afa1b5cd53",
      "title": "Facebook Story",
      "artist": "Frank Ocean",
      "album": "Blonde",
      "duration": 0,
      "file_path": "/home/jscyril/Music/FLAC/complete/transon/2016 - Blonde/12. Facebook Story.flac",
      "genre": "Art Pop; Pop; Rnb; Soul",
      "year": 2016,
      "track_number": 12,
      "created_at": "2026-01-28T16:20:22.470384532+05:30"
    },
    "track-de60417dbfb1c891": {
      "id": "track-de60417dbfb1c891",
      "title": "Ma meilleure ennemie",
      "artist": "Stromae",
      "album": "Arcane League of Legends: Season Two Original Soundtrack",
      "duration": 0,
      "file_path": "/home/jscyril/Music/FLAC/complete/Arcane League of Legends - Season Two Original Soundtrack (2024)/Arcane - Arcane League of Legends - Season Two Original Soundtrack - 16 - Ma meilleure ennemie.flac",
      "genre": "Art Pop",
      "year": 2024,
      "track_number": 16,
      "created_at": "2026-01-28T16:20:22.437096783+05:30"
    },
    "track-def98237fda8deeb": {
      "id": "track-def98237fda8deeb",
      "title": "Headlock",
      "artist": "Imogen Heap",
      "album": "Speak for Yourself",
      "duration": 0,
      "file_path": "/home/jscyril/Music/FLAC/complete/mylibrarycantbethiscute/Speak for Yourself/01 Headlock.flac",
      "genre": "",
      "year": 2012,
      "track_number": 1,
      "created_at": "2026-01-28T16:20:22.464410426+05:30"
    },
    "track-df4a0d0965c405df": {
      "id": "track-df4a0d0965c405df",
      "title": "Can't GET Over YOU (Featuring Clams Casino)",
      "artist": "Joji",
      "album": "BALLADS 1",
      "duration": 0,
      "file_path": "/home/jscyril/Music/FLAC/complete/BALLADS 1/Joji_BALLADS 1_05_CAN’T GET OVER YOU.flac",
      "genre": "R\u0026B",
      "year": 2018,
      "track_number": 5,
      "created_at": "2026-01-28T16:20:22.440125915+05:30"
    },
    "track-e263c271efab644f": {
      "id": "track-e263c271efab644f",
      "title": "Remember Me",
      "artist": "d4vd",
      "album": "Arcane League of Legends: Season 2 (Soundtrack from the Animated Series)",
      "duration": 0,
      "file_path": "/home/jscyril/Music/FLAC/complete/Arcane League of Legends  Season 2 (Soundtrack from the Animated Series)/1-09 - Remember Me.flac",
      "genre": "Soundtrack",
      "year": 2024,
      "track_number": 9,
      "created_at": "2026-01-28T16:20:22.435547396+05:30"
    },
    "track-e3aa70a6c2ab93b3": {
      "id": "track-e3aa70a6c2ab93b3",
      "title": "Yeah Right",
      "artist": "Joji",
      "album": "BALLADS 1",
      "duration": 0,
      "file_path": "/home/jscyril/Music/FLAC/complete/BALLADS 1/Joji_BALLADS 1_06_YEAH RIGHT.flac",
      "genre": "R\u0026B",
      "year": 2018,
      "track_number": 6,
      "created_at": "2026-01-28T16:20:22.440520575+05:30"
    },
    "track-e5e0d72dbff53e9e": {
      "id": "track-e5e0d72dbff53e9e",
      "title": "Sucker (from the series Arcane League of Legends)",
      "artist": "Marcus King",
      "album": "Arcane League of Legends: Season 2 (Soundtrack from the Animated Series)",
      "duration": 0,
      "file_path": "/home/jscyril/Music/FLAC/complete/Arcane League of Legends - Soundtrack from the Animated Series [Season 2]/03. Marcus King - Sucker (from the series Arcane League of Legends).flac",
      "genre": "",
      "year": 2024,
      "track_number": 3,
      "created_at": "2026-01-28T16:20:22.436943104+05:30"
    },
    "track-e89fbcfbac98e5a4": {
      "id": "track-e89fbcfbac98e5a4",
      "title": "WHY AM I Still IN LA (Featuring Shlohmo \u0026 D33j)",
      "artist": "Joji",
      "album": "BALLADS 1",
      "duration": 0,
      "file_path": "/home/jscyril/Music/FLAC/complete/BALLADS 1/Joji_BALLADS 1_07_WHY AM I STILL IN LA.flac",
      "genre": "R\u0026B",
      "year": 2018,
      "track_number": 7,
      "created_at": "2026-01-28T16:20:22.440552064+05:30"
    },
    "track-ed893c3712f63e40": {
      "id": "track-ed893c3712f63e40",
      "title": "Wanted U",
      "artist": "Joji",
      "album": "BALLADS 1",
      "duration": 0,
      "file_path": "/home/jscyril/Music/FLAC/complete/BALLADS 1/Joji_BALLADS 1_04_WANTED U.flac",
      "genre": "R\u0026B",
      "year": 2018,
      "track_number": 4,
      "created_at": "2026-01-28T16:20:22.440258493+05:30"
    },
    "track-edd731a3d7332075": {
      "id": "track-edd731a3d7332075",
      "title": "Fluxxwave",
      "artist": "Clovis Reyes",
      "album": "Fluxxwave",
      "duration": 0,
      "file_path": "/home/jscyril/Music/FLAC/complete/Clovis Reyes - Fluxxwave.flac",
      "genre": "",
      "year": 2023,
      "track_number": 0,
      "created_at": "2026-01-28T16:20:22.441940408+05:30"
    },
    "track-eff13ed617c82ef5": {
      "id": "track-eff13ed617c82ef5",
      "title": "R.I.P. (Featuring Trippie Redd)",
      "artist": "Joji",
      "album": "BALLADS 1",
      "duration": 0,
      "file_path": "/home/jscyril/Music/FLAC/complete/BALLADS 1/Joji_BALLADS 1_10_R.I.P.flac",
      "genre": "R\u0026B",
      "year": 2018,
      "track_number": 10,
      "created_at": "2026-01-28T16:20:22.441012417+05:30"
    },
    "track-f0c488a3678fbfa7": {
      "id": "track-f0c488a3678fbfa7",
      "title": "Nights",
      "artist": "Frank Ocean",
      "album": "Blonde",
      "duration": 0,
      "file_path": "/home/jscyril/Music/FLAC/complete/transon/2016 - Blonde/09. Nights.flac",
      "genre": "Art Pop; Pop; Rnb; Soul",
      "year": 2016,
      "track_number": 9,
      "created_at": "2026-01-28T16:20:22.469063444+05:30"
    },
    "track-f17f36680e71966c": {
      "id": "track-f17f36680e71966c",
      "title": "Glimpse Of Us",
      "artist": "Joji",
      "album": "Glimpse Of Us",
      "duration": 0,
      "file_path": "/home/jscyril/Music/FLAC/complete/SMITHEREENS-1/1-01 Glimpse of Us.flac",
      "genre": "Lo-Fi Hip Hop",
      "year": 2022,
      "track_number": 1,
      "created_at": "2026-01-28T16:20:22.4564797+05:30"
    },
    "track-f715982e339fc344": {
      "id": "track-f715982e339fc344",
      "title": "Daylight",
      "artist": "Joji \u0026 Diplo",
      "album": "Nectar",
      "duration": 0,
      "file_path": "/home/jscyril/Music/FLAC/complete/Nectar/Joji_Nectar_04_Daylight.flac",
      "genre": "",
      "year": 2020,
      "track_number": 4,
      "created_at": "2026-01-28T16:20:22.44970886+05:30"
    },
    "track-fb6ba8b305ebcd45": {
      "id": "track-fb6ba8b305ebcd45",
      "title": "Futura Free",
      "artist": "Frank Ocean",
      "album": "Blonde",
      "duration": 0,
      "file_path": "/home/jscyril/Music/FLAC/complete/transon/2016 - Blonde/17. Futura Free.flac",
      "genre": "Art Pop; Pop; Rnb; Soul",
      "year": 2016,
      "track_number": 17,
      "created_at": "2026-01-28T16:20:22.472060055+05:30"
    },
    "track-fd3f7674c4685937": {
      "id": "track-fd3f7674c4685937",
      "title": "The Fallen",
      "artist": "Caleb Bryant",
      "album": "The Fallen",
      "duration": 0,
      "file_path": "/home/jscyril/Music/FLAC/complete/Caleb Bryant - The Fallen.flac",
      "genre": "",
      "year": 2023,
      "track_number": 0,
      "created_at": "2026-01-28T16:20:22.442017703+05:30"
    },
    "track-fff70a72ae97cc3f": {
      "id": "track-fff70a72ae97cc3f",
      "title": "High Hopes (feat. Omar Apollo)",
      "artist": "Joji",
      "album": "Nectar",
      "duration": 0,
      "file_path": "/home/jscyril/Music/FLAC/complete/Nectar/Joji_Nectar_09_High Hopes.flac",
      "genre": "",
      "year": 2020,
      "track_number": 9,
      "created_at": "2026-01-28T16:20:22.452565638+05:30"
    }
  },
  "scan_paths": [
    "/home/jscyril/Music/FLAC/complete"
  ],
  "last_scanned": "2026-01-28T16:20:22.472084861+05:30",
  "total_tracks": 105
}